analyzer.py
main.py
naming.py
parser.py
utils.py
tf_guard-1.0.2.dist-info/licenses/LICENSE
tf_guard-1.0.2.dist-info/METADATA
tf_guard-1.0.2.dist-info/WHEEL
tf_guard-1.0.2.dist-info/entry_points.txt
tf_guard-1.0.2.dist-info/top_level.txt
tf_guard-1.0.2.dist-info/RECORD
