Metadata-Version: 2.4
Name: tf-guard
Version: 1.0.2
License-File: LICENSE
Requires-Dist: click
Requires-Dist: openai
Requires-Dist: rich
Requires-Dist: python-dotenv
Dynamic: license-file
Dynamic: requires-dist
